scflcore/__init__.py
scflcore/core.py
scflcore-0.0.9.dist-info/METADATA
scflcore-0.0.9.dist-info/WHEEL
scflcore-0.0.9.dist-info/top_level.txt
scflcore-0.0.9.dist-info/RECORD
