Metadata-Version: 2.1
Name: scflcore
Version: 0.0.9
Summary: Function core package by SScefaLI
Home-page: UNKNOWN
Author: SScefaLI
Author-email: birka11@list.ru
License: UNKNOWN
Platform: UNKNOWN
Classifier: Programming Language :: Python :: 3
Classifier: License :: OSI Approved :: MIT License
Classifier: Operating System :: OS Independent
Requires-Python: >=3.8
Requires-Dist: requests
